odvc/__init__.py
odvc/_version.py
odvc/formulas.py
odvc/parse_formula_terms.py
odvc-1.0.0.dist-info/LICENSE.txt
odvc-1.0.0.dist-info/METADATA
odvc-1.0.0.dist-info/WHEEL
odvc-1.0.0.dist-info/top_level.txt
odvc-1.0.0.dist-info/zip-safe
odvc-1.0.0.dist-info/RECORD
